<?xml version="1.0" encoding="us-ascii"?>
<Catalog>
    <CTexture id="Decal_Protoss_0001_01">
        <File value="Assets\Textures\decal_protoss_0001_01.dds"/>
    </CTexture>
    <CTexture id="Decal_Protoss_0004_01">
        <File value="Assets\Textures\decal_protoss_0004_01.dds"/>
    </CTexture>
    <CTexture id="Decal_Protoss_0005_01">
        <File value="Assets\Textures\decal_protoss_0005_01.dds"/>
    </CTexture>
    <CTexture id="Decal_Protoss_0006_01">
        <File value="Assets\Textures\decal_protoss_0006_01.dds"/>
    </CTexture>
    <CTexture id="Decal_Protoss_0008_01">
        <File value="Assets\Textures\decal_protoss_0008_01.dds"/>
    </CTexture>
    <CTexture id="Decal_Protoss_0009_01">
        <File value="Assets\Textures\decal_protoss_0009_01.dds"/>
    </CTexture>
    <CTexture id="Decal_Protoss_0011_01">
        <File value="Assets\Textures\decal_protoss_0011_01.dds"/>
    </CTexture>
    <CTexture id="Decal_Protoss_0015_01">
        <File value="Assets\Textures\decal_protoss_0015_01.dds"/>
    </CTexture>
    <CTexture id="Decal_Protoss_0017_01">
        <File value="Assets\Textures\decal_protoss_0017_01.dds"/>
    </CTexture>
    <CTexture id="Decal_Protoss_0019_01">
        <File value="Assets\Textures\decal_protoss_0019_01.dds"/>
    </CTexture>
    <CTexture id="Decal_Protoss_0021_01">
        <File value="Assets\Textures\decal_protoss_0021_01.dds"/>
    </CTexture>
    <CTexture id="Decal_Terran_0001_01">
        <File value="Assets\Textures\decal_terran_0001_01.dds"/>
    </CTexture>
    <CTexture id="Decal_Terran_0004_01">
        <File value="Assets\Textures\decal_terran_0004_01.dds"/>
    </CTexture>
    <CTexture id="Decal_Terran_0005_01">
        <File value="Assets\Textures\decal_terran_0005_01.dds"/>
    </CTexture>
    <CTexture id="Decal_Terran_0006_01">
        <File value="Assets\Textures\decal_terran_0006_01.dds"/>
    </CTexture>
    <CTexture id="Decal_Terran_0008_01">
        <File value="Assets\Textures\decal_terran_0008_01.dds"/>
    </CTexture>
    <CTexture id="Decal_Terran_0009_01">
        <File value="Assets\Textures\decal_terran_0009_01.dds"/>
    </CTexture>
    <CTexture id="Decal_Terran_0011_01">
        <File value="Assets\Textures\decal_terran_0011_01.dds"/>
    </CTexture>
    <CTexture id="Decal_Terran_0015_01">
        <File value="Assets\Textures\decal_terran_0015_01.dds"/>
    </CTexture>
    <CTexture id="Decal_Terran_0017_01">
        <File value="Assets\Textures\decal_terran_0017_01.dds"/>
    </CTexture>
    <CTexture id="Decal_Terran_0019_01">
        <File value="Assets\Textures\decal_terran_0019_01.dds"/>
    </CTexture>
    <CTexture id="Decal_Terran_0021_01">
        <File value="Assets\Textures\decal_terran_0021_01.dds"/>
    </CTexture>
    <CTexture id="Decal_Zerg_0001_01">
        <File value="Assets\Textures\decal_zerg_0001_01.dds"/>
    </CTexture>
    <CTexture id="Decal_Zerg_0004_01">
        <File value="Assets\Textures\decal_zerg_0004_01.dds"/>
    </CTexture>
    <CTexture id="Decal_Zerg_0005_01">
        <File value="Assets\Textures\decal_zerg_0005_01.dds"/>
    </CTexture>
    <CTexture id="Decal_Zerg_0006_01">
        <File value="Assets\Textures\decal_zerg_0006_01.dds"/>
    </CTexture>
    <CTexture id="Decal_Zerg_0008_01">
        <File value="Assets\Textures\decal_zerg_0008_01.dds"/>
    </CTexture>
    <CTexture id="Decal_Zerg_0009_01">
        <File value="Assets\Textures\decal_zerg_0009_01.dds"/>
    </CTexture>
    <CTexture id="Decal_Zerg_0011_01">
        <File value="Assets\Textures\decal_zerg_0011_01.dds"/>
    </CTexture>
    <CTexture id="Decal_Zerg_0015_01">
        <File value="Assets\Textures\decal_zerg_0015_01.dds"/>
    </CTexture>
    <CTexture id="Decal_Zerg_0017_01">
        <File value="Assets\Textures\decal_zerg_0017_01.dds"/>
    </CTexture>
    <CTexture id="Decal_Zerg_0019_01">
        <File value="Assets\Textures\decal_zerg_0019_01.dds"/>
    </CTexture>
    <CTexture id="Decal_Zerg_0021_01">
        <File value="Assets\Textures\decal_zerg_0021_01.dds"/>
    </CTexture>
</Catalog>
